rai_experiments/__init__.py
rai_experiments/models/__init__.py
rai_experiments/models/_resnet_blocks.py
rai_experiments/models/pretrained.py
rai_experiments/models/resnet.py
rai_experiments/models/small_resnet.py
rai_experiments/utils/__init__.py
rai_experiments/utils/imagenet_labels.py
rai_experiments/utils/visualizations.py
rai_experiments-0.2.0.dist-info/LICENSE.txt
rai_experiments-0.2.0.dist-info/METADATA
rai_experiments-0.2.0.dist-info/WHEEL
rai_experiments-0.2.0.dist-info/top_level.txt
rai_experiments-0.2.0.dist-info/RECORD
